aidiscuss/__init__.py
aidiscuss/alembic.ini
aidiscuss/cli.py
aidiscuss/main.py
aidiscuss/alembic/env.py
aidiscuss/alembic/script.py.mako
aidiscuss/app/__init__.py
aidiscuss/app/core/__init__.py
aidiscuss/app/core/config.py
aidiscuss/app/core/encryption.py
aidiscuss/app/core/port_manager.py
aidiscuss/app/db/__init__.py
aidiscuss/app/db/base.py
aidiscuss/app/db/seed_providers.py
aidiscuss/app/models/__init__.py
aidiscuss/app/models/admin_action.py
aidiscuss/app/models/agent.py
aidiscuss/app/models/chat_config.py
aidiscuss/app/models/consensus_tracking.py
aidiscuss/app/models/conversation.py
aidiscuss/app/models/conversation_memory.py
aidiscuss/app/models/document.py
aidiscuss/app/models/provider.py
aidiscuss/app/models/provider_key.py
aidiscuss/app/models/quality_metric.py
aidiscuss/app/models/settings.py
aidiscuss/app/routers/__init__.py
aidiscuss/app/routers/admin_override.py
aidiscuss/app/routers/agents.py
aidiscuss/app/routers/analytics.py
aidiscuss/app/routers/chat.py
aidiscuss/app/routers/chat_config.py
aidiscuss/app/routers/conversations.py
aidiscuss/app/routers/export.py
aidiscuss/app/routers/health.py
aidiscuss/app/routers/keys.py
aidiscuss/app/routers/memory.py
aidiscuss/app/routers/offline.py
aidiscuss/app/routers/provider_keys.py
aidiscuss/app/routers/providers.py
aidiscuss/app/routers/quality.py
aidiscuss/app/routers/rag.py
aidiscuss/app/routers/rag_control.py
aidiscuss/app/routers/settings.py
aidiscuss/app/routers/sync.py
aidiscuss/app/routers/tools.py
aidiscuss/app/services/__init__.py
aidiscuss/app/services/analytics_service.py
aidiscuss/app/services/broadcast.py
aidiscuss/app/services/cache.py
aidiscuss/app/services/consensus_service.py
aidiscuss/app/services/human_response_handler.py
aidiscuss/app/services/llm_provider.py
aidiscuss/app/services/memory_service.py
aidiscuss/app/services/offline_service.py
aidiscuss/app/services/orchestrator_parallel.py
aidiscuss/app/services/persona_service.py
aidiscuss/app/services/quality_service.py
aidiscuss-0.1.0.dist-info/licenses/LICENSE
aidiscuss-0.1.0.dist-info/METADATA
aidiscuss-0.1.0.dist-info/WHEEL
aidiscuss-0.1.0.dist-info/entry_points.txt
aidiscuss-0.1.0.dist-info/top_level.txt
aidiscuss-0.1.0.dist-info/RECORD
